nv_attestation_sdk/__init__.py
nv_attestation_sdk/attestation.py
nv_attestation_sdk/gpu/__init__.py
nv_attestation_sdk/gpu/attest_gpu_local.py
nv_attestation_sdk/gpu/attest_gpu_remote.py
nv_attestation_sdk/nvswitch/__init__.py
nv_attestation_sdk/nvswitch/attest_nvswitch_local.py
nv_attestation_sdk/nvswitch/attest_nvswitch_remote.py
nv_attestation_sdk/utils/__init__.py
nv_attestation_sdk/utils/claim_utils.py
nv_attestation_sdk/utils/config.py
nv_attestation_sdk/utils/headers.py
nv_attestation_sdk/utils/local_utils.py
nv_attestation_sdk/utils/logging_config.py
nv_attestation_sdk/utils/nras_utils.py
nv_attestation_sdk/utils/unified_eat_parser.py
nv_attestation_sdk/verifiers/__init__.py
nv_attestation_sdk/verifiers/nv_switch_verifier/__init__.py
nv_attestation_sdk/verifiers/nv_switch_verifier/attestation/__init__.py
nv_attestation_sdk/verifiers/nv_switch_verifier/attestation/spdm_msrt_req_msg.py
nv_attestation_sdk/verifiers/nv_switch_verifier/attestation/spdm_msrt_resp_msg.py
nv_attestation_sdk/verifiers/nv_switch_verifier/certs/verifier_RIM_root.pem
nv_attestation_sdk/verifiers/nv_switch_verifier/certs/verifier_device_root.pem
nv_attestation_sdk/verifiers/nv_switch_verifier/config.py
nv_attestation_sdk/verifiers/nv_switch_verifier/exceptions/__init__.py
nv_attestation_sdk/verifiers/nv_switch_verifier/models/__init__.py
nv_attestation_sdk/verifiers/nv_switch_verifier/models/nvswitch.py
nv_attestation_sdk/verifiers/nv_switch_verifier/nscq/README.md
nv_attestation_sdk/verifiers/nv_switch_verifier/nscq/__init__.py
nv_attestation_sdk/verifiers/nv_switch_verifier/nscq/nscq_attestation.h
nv_attestation_sdk/verifiers/nv_switch_verifier/nscq/nscq_attestation_path.h
nv_attestation_sdk/verifiers/nv_switch_verifier/nscq/paths.py
nv_attestation_sdk/verifiers/nv_switch_verifier/nscq/pynscq.py
nv_attestation_sdk/verifiers/nv_switch_verifier/nvswitch_admin.py
nv_attestation_sdk/verifiers/nv_switch_verifier/nvswitch_admin_utils.py
nv_attestation_sdk-2.6.4.dist-info/METADATA
nv_attestation_sdk-2.6.4.dist-info/WHEEL
nv_attestation_sdk-2.6.4.dist-info/licenses/LICENSE
nv_attestation_sdk-2.6.4.dist-info/RECORD
