Metadata-Version: 2.4
Name: nv-attestation-sdk
Version: 2.6.4
Summary: The Attestation SDK provides developers with a easy to use APIs for implementing attestation capabilities into their applications.
License-File: LICENSE
Keywords: confidential-computing,local-gpu-verifier,attestation,NVIDIA
Author: Karthik Jayaraman
Author-email: kjayaraman@nvidia.com
Requires-Python: >=3.7
Classifier: Programming Language :: Python :: 3
Classifier: Programming Language :: Python :: 3.7
Classifier: Programming Language :: Python :: 3.8
Classifier: Programming Language :: Python :: 3.9
Classifier: Programming Language :: Python :: 3.10
Classifier: Programming Language :: Python :: 3.11
Classifier: Programming Language :: Python :: 3.12
Classifier: Programming Language :: Python :: 3.13
Classifier: Programming Language :: Python :: 3.14
Requires-Dist: PyJWT (==2.7.0)
Requires-Dist: build (>=0.7.0)
Requires-Dist: cryptography (==43.0.1)
Requires-Dist: ecdsa (==0.18.0)
Requires-Dist: nv-local-gpu-verifier (==2.6.4)
Requires-Dist: nvidia-ml-py (>=12.535.77)
Requires-Dist: parameterized (==0.9.0)
Requires-Dist: pyOpenSSL (==24.2.1)
Requires-Dist: pyjwt (>=2.7.0,<2.8.0)
Requires-Dist: pylint (>=2.9.6)
Requires-Dist: pytest (==8.1.1)
Requires-Dist: pytest-cov (>=5.0.0)
Requires-Dist: requests (>=2.32.3,<2.33.0)
Requires-Dist: signxml (==3.2.0)
Requires-Dist: twine (>=3.7.1)
Requires-Dist: xmlschema (==2.2.3)
